pyminr/__init__.py
pyminr/lib/libminr.dylib
pyminr-0.1.2.dist-info/LICENSE
pyminr-0.1.2.dist-info/METADATA
pyminr-0.1.2.dist-info/WHEEL
pyminr-0.1.2.dist-info/top_level.txt
pyminr-0.1.2.dist-info/RECORD
